{"version": 0.6, "generator": "Overpass API 0.7.62.5 1bd436f1", "osm3s": {"timestamp_osm_base": "2025-03-11T12:51:14Z", "copyright": "The data included in this document is from www.openstreetmap.org. The data is made available under ODbL."}, "elements": [{"type": "node", "id": 1500853555, "lat": 43.6926868, "lon": -79.4657378, "tags": {"brand": "FreshCo", "brand:wikidata": "Q5502915", "brand:wikipedia": "en:FreshCo", "name": "FreshCo", "shop": "supermarket"}}, {"type": "node", "id": 5642653387, "lat": 43.6921034, "lon": -79.4672958, "tags": {"name": "C-Mart", "shop": "convenience"}}, {"type": "node", "id": 7559857489, "lat": 43.6906715, "lon": -79.4735358, "tags": {"shop": "convenience"}}, {"type": "node", "id": 11582725856, "lat": 43.6913936, "lon": -79.4702819, "tags": {"name": "G&J West Indian Grocery & Kitchen", "shop": "supermarket"}}, {"type": "node", "id": 11582745976, "lat": 43.6918419, "lon": -79.468344, "tags": {"name": "Family Food Mart", "shop": "convenience"}}]}