{"version": 0.6, "generator": "Overpass API 0.7.62.5 1bd436f1", "osm3s": {"timestamp_osm_base": "2025-02-24T16:33:30Z", "copyright": "The data included in this document is from www.openstreetmap.org. The data is made available under ODbL."}, "elements": [{"type": "node", "id": 365652850, "lat": 43.7580862, "lon": -79.5201689}, {"type": "node", "id": 365652855, "lat": 43.7580511, "lon": -79.5202256}, {"type": "node", "id": 4177416984, "lat": 43.7575572, "lon": -79.5188635, "tags": {"amenity": "cafe", "brand": "Tim Hortons", "brand:wikidata": "Q175106", "brand:wikipedia": "en:Tim Hortons", "cuisine": "coffee_shop", "name": "Tim Hortons", "takeaway": "yes"}}, {"type": "node", "id": 6370679347, "lat": 43.7581005, "lon": -79.5200007}, {"type": "node", "id": 6370679359, "lat": 43.7580572, "lon": -79.5199354}, {"type": "node", "id": 6370679378, "lat": 43.758111, "lon": -79.520166}, {"type": "node", "id": 6371265843, "lat": 43.769471, "lon": -79.5218046, "tags": {"amenity": "cafe", "name": "Hoang Viet"}}, {"type": "node", "id": 11179035876, "lat": 43.7580186, "lon": -79.5202117}, {"type": "node", "id": 11179035877, "lat": 43.7580498, "lon": -79.5199363}, {"type": "node", "id": 11179035878, "lat": 43.7580576, "lon": -79.5200564}, {"type": "node", "id": 11179035879, "lat": 43.7580093, "lon": -79.520062}, {"type": "way", "id": 1206414594, "nodes": [365652855, 11179035876, 11179035879, 11179035878, 11179035877, 6370679359, 6370679347, 6370679378, 365652850, 365652855], "tags": {"addr:city": "Toronto", "addr:housenumber": "1", "addr:postcode": "M3N 3A1", "addr:province": "Ontario", "addr:street": "York Gate Boulevard", "addr:unit": "B1", "amenity": "cafe", "brand": "Tim Hortons", "brand:wikidata": "Q175106", "brand:wikipedia": "en:Tim Hortons", "cuisine": "coffee_shop", "indoor": "yes", "level": "0", "name": "Tim Hortons", "opening_hours": "Mo-Fr 10:00-21:00; Sa 9:30-18:00; Su 12:00-17:00", "outdoor_seating": "yes", "takeaway": "yes"}}]}