{"version": 0.6, "generator": "Overpass API 0.7.62.5 1bd436f1", "osm3s": {"timestamp_osm_base": "2025-02-19T15:56:00Z", "copyright": "The data included in this document is from www.openstreetmap.org. The data is made available under ODbL."}, "elements": [{"type": "node", "id": 366553178, "lat": 43.6897851, "lon": -79.4770733}, {"type": "node", "id": 366553180, "lat": 43.6901989, "lon": -79.4754314}, {"type": "node", "id": 366553182, "lat": 43.6905001, "lon": -79.475561}, {"type": "node", "id": 366553183, "lat": 43.6909111, "lon": -79.4756372}, {"type": "node", "id": 366553184, "lat": 43.6911657, "lon": -79.4758738}, {"type": "node", "id": 366553187, "lat": 43.6923444, "lon": -79.4774387}, {"type": "node", "id": 366553189, "lat": 43.6921028, "lon": -79.4785217}, {"type": "node", "id": 366553191, "lat": 43.6902941, "lon": -79.4773775}, {"type": "node", "id": 366553193, "lat": 43.6900206, "lon": -79.4772649}, {"type": "node", "id": 366554728, "lat": 43.693324, "lon": -79.4777349}, {"type": "node", "id": 366554730, "lat": 43.693993, "lon": -79.4748205}, {"type": "node", "id": 366554733, "lat": 43.693027, "lon": -79.4746325}, {"type": "node", "id": 366554735, "lat": 43.6925834, "lon": -79.4767404}, {"type": "node", "id": 6300020689, "lat": 43.6901727, "lon": -79.4773275}, {"type": "node", "id": 6300020693, "lat": 43.6907246, "lon": -79.4774205}, {"type": "node", "id": 6300020694, "lat": 43.6903309, "lon": -79.47723}, {"type": "node", "id": 6300020695, "lat": 43.6906179, "lon": -79.4778804}, {"type": "node", "id": 6300020696, "lat": 43.6918543, "lon": -79.4784093}, {"type": "node", "id": 12385656915, "lat": 43.6907105, "lon": -79.4755074}, {"type": "node", "id": 12385656916, "lat": 43.6905341, "lon": -79.4754175}, {"type": "way", "id": 32596010, "nodes": [366553178, 366553180, 366553182, 12385656916, 12385656915, 366553183, 366553184, 366553187, 366553189, 6300020696, 6300020695, 6300020693, 6300020694, 366553191, 6300020689, 366553193, 366553178], "tags": {"addr:city": "Toronto", "addr:housenumber": "2690", "addr:postcode": "M6M 1T9", "addr:street": "Eglinton Avenue West", "amenity": "school", "fax": "+1-416-394-3416", "isced:level": "3", "mascot": "Mustangs", "name": "York Memorial Collegiate Institute", "operator": "Toronto District School Board", "operator:short": "TDSB", "operator:type": "public", "operator:wikidata": "Q1189302", "operator:wikipedia": "en:Toronto District School Board", "phone": "+1-416-394-3000", "school:language": "english", "source": "Contains public sector Datasets made available under the City of Toronto's Open Data License v2.0.", "website": "https://schoolweb.tdsb.on.ca/yorkmemorial", "wikidata": "Q8055496", "wikipedia": "en:York Memorial Collegiate Institute"}}, {"type": "way", "id": 32596138, "nodes": [366554728, 366554730, 366554733, 366554735, 366554728], "tags": {"addr:city": "York", "addr:housenumber": "1900", "addr:postcode": "M6M 3X7", "addr:street": "Keele Street", "amenity": "school", "fax": "+1-416-394-4092", "isced:level": "1;2", "name": "Charles E Webster Public School", "operator": "Toronto District School Board", "operator:short": "TDSB", "operator:type": "public", "operator:wikidata": "Q1189302", "operator:wikipedia": "en:Toronto District School Board", "phone": "+1-416-394-2250", "school:language": "english", "source": "Contains public sector Datasets made available under the City of Toronto's Open Data License v2.0.", "website": "https://schoolweb.tdsb.on.ca/cewebster"}}]}